mine_init/__init__.py
mine_init/core.py
mine_init/extra_files/__init__.py
mine_init/extra_files/log4j2.xml
mine_init/utils.py
mine_init-0.2.2.dist-info/entry_points.txt
mine_init-0.2.2.dist-info/LICENSE.rst
mine_init-0.2.2.dist-info/WHEEL
mine_init-0.2.2.dist-info/METADATA
mine_init-0.2.2.dist-info/RECORD
