Metadata-Version: 2.1
Name: mine-init
Version: 0.2.2
Summary: A docker friendly startup routine for Minecraft servers.
Home-page: https://gitlab.routh.io/minecraft/tools/mine-init
License: MIT
Author: Chris Routh
Author-email: chris@routh.io
Requires-Python: >=3.6
Classifier: License :: OSI Approved :: MIT License
Classifier: Programming Language :: Python :: 3
Classifier: Programming Language :: Python :: 3.6
Classifier: Programming Language :: Python :: 3.7
Classifier: Programming Language :: Python :: 3.8
Requires-Dist: packmaker (==0.4.3)
Project-URL: Repository, https://gitlab.routh.io/minecraft/tools/mine-init
